argocd/__init__.py
argocd/config.py
argocd/services/__init__.py
argocd/services/certificate.py
argocd/services/repository.py
argocd/services/repository_creds.py
argocd/services/settings.py
argocd/services/version.py
argocd-0.5.0.dist-info/LICENSE
argocd-0.5.0.dist-info/METADATA
argocd-0.5.0.dist-info/WHEEL
argocd-0.5.0.dist-info/top_level.txt
argocd-0.5.0.dist-info/RECORD
