Metadata-Version: 2.1
Name: argocd
Version: 0.5.0
Summary: Python client for ArgoCD
Author-email: Mayank Pathak <onlinejudge95@gmail.com>
Project-URL: Homepage, https://github.com/onlinejudge95/argopy
Project-URL: Bug Tracker, https://github.com/onlinejudge95/argopy/issues
Classifier: Development Status :: 3 - Alpha
Classifier: Environment :: Other Environment
Classifier: Intended Audience :: Developers
Classifier: Natural Language :: English
Classifier: Operating System :: POSIX :: Linux
Classifier: Programming Language :: Python :: 3.10
Classifier: Topic :: Software Development :: Libraries :: Python Modules
Classifier: Typing :: Typed
License-File: LICENSE
